mauritstestpackage/__init__.py
mauritstestpackage/locales/nl/LC_MESSAGES/mauritstestpackage.mo
mauritstestpackage/locales/nl/LC_MESSAGES/mauritstestpackage.po
mauritstestpackage2-3.0.7.dist-info/METADATA
mauritstestpackage2-3.0.7.dist-info/WHEEL
mauritstestpackage2-3.0.7.dist-info/top_level.txt
mauritstestpackage2-3.0.7.dist-info/RECORD
