Metadata-Version: 2.1
Name: mauritstestpackage2
Version: 3.0.7
Summary: Test package from Maurits for uploading to PyPI.
Home-page: https://github.com/mauritsvanrees/mauritstestpackage
Author: Maurits van Rees
Author-email: maurits@vanrees.org
License: GPL
Keywords: test release pypi
Classifier: Development Status :: 3 - Alpha
Classifier: Intended Audience :: Developers
Classifier: License :: OSI Approved :: GNU General Public License (GPL)
Classifier: Programming Language :: Python
Classifier: Programming Language :: Python :: 3
Classifier: Programming Language :: Python :: 3.11
Requires-Python: >=3.8
